README.md
setup.py
pygame_truly_centered_button.egg-info/PKG-INFO
pygame_truly_centered_button.egg-info/SOURCES.txt
pygame_truly_centered_button.egg-info/dependency_links.txt
pygame_truly_centered_button.egg-info/requires.txt
pygame_truly_centered_button.egg-info/top_level.txt
pygamecentering/__init__.py
pygamecentering/centering.py
pygamecentering/generate_offset_data.py
pygamecentering/offset_linear_regression.py