Metadata-Version: 2.1
Name: pygame-truly-centered-button
Version: 2.13
Summary: A Pygame library of a button class with properly-centered text!
Home-page: https://github.com/mchen610/pygame-truly-centered-button
Author: Melvin Chen
Author-email: melvinchen610@gmail.com
Requires-Dist: pygame
Requires-Dist: numpy
Requires-Dist: joblib
Requires-Dist: scipy
Requires-Dist: threadpoolctl
Requires-Dist: scikit-learn
